{
    "RefreshTokenValidity": 15,
    "AccessTokenValidity": 30,
    "IdTokenValidity": 30,
    "TokenValidityUnits": {
        "AccessToken": "minutes",
        "IdToken": "minutes",
        "RefreshToken": "days"
    },
    "ExplicitAuthFlows": [
        "ALLOW_ADMIN_USER_PASSWORD_AUTH",
        "ALLOW_CUSTOM_AUTH",
        "ALLOW_REFRESH_TOKEN_AUTH",
        "ALLOW_USER_PASSWORD_AUTH",
        "ALLOW_USER_SRP_AUTH"
    ],
    "SupportedIdentityProviders": [
        "COGNITO"
    ],
    "CallbackURLs": [
        "https://127.0.0.1:8000/"
    ],
    "AllowedOAuthFlows": [
        "code"
    ],
    "AllowedOAuthScopes": [
        "aws.cognito.signin.user.admin",
        "openid"
    ],
    "GenerateSecret": true,
    "AllowedOAuthFlowsUserPoolClient": true,
    "PreventUserExistenceErrors": "ENABLED",
    "EnableTokenRevocation": true,
    "EnablePropagateAdditionalUserContextData": false,
    "AuthSessionValidity": 5
}